{
  "resourceType": "Library",
  "id": "BCTrastuzumabEmtansineRule2",
  "url": "https://nhicore.nhi.gov.tw/cql/Library/BCTrastuzumabEmtansineRule2",
  "version": "1.0.0",
  "name": "BCTrastuzumabEmtansineRule2",
  "title": "Trastuzumab Emtansine給付規定-TrastuzumabEmtansine Rule2",
  "status": "draft",
  "type": {
    "coding": [
      {
        "system": "http://terminology.hl7.org/CodeSystem/library-type",
        "code": "logic-library"
      }
    ]
  },
  "date": "2026-05-08",
  "description": "此 Library 為乳癌（晚期乳癌）患者於申請使用 Trastuzumab Emtansine 之給付檢核條件。",
  "content": [
    {
      "id": "ig-loader-BCTrastuzumabEmtansineRule2.cql"
    }
  ]
}
